uploads/__init__.py
uploads/main.py
uploads/test_upload.py
uploads-1.1.dist-info/METADATA
uploads-1.1.dist-info/WHEEL
uploads-1.1.dist-info/top_level.txt
uploads-1.1.dist-info/RECORD
