Metadata-Version: 2.1
Name: uploads
Version: 1.1
Summary: a pythonic uploader in UI automation, to replace autoit in uploading of UI browser
Home-page: https://gitee.com/teark/upload.git
Author: TEARK
Author-email: 913355434@qq.com
Classifier: Programming Language :: Python :: 3
Classifier: License :: OSI Approved :: MIT License
Classifier: Operating System :: OS Independent
Requires-Python: >=3.6
Requires-Dist: pywin32
